{
  "Claws": "Claw",
  "Daggers": "Dagger",
  "Wands": "Wand",
  "One Hand Swords": "Sword",
  "Thrusting One Hand Swords": "Sword",
  "One Hand Axes": "Axe",
  "One Hand Maces": "Mace",
  "Sceptres": "Sceptre",
  "Bows": "Bow",
  "Staves": "Staff",
  "Two Hand Swords": "Sword",
  "Two Hand Axes": "Axe",
  "Two Hand Maces": "Mace",
  "Fishing Rods": "Fishing Rod",
  "Gloves": "Gloves",
  "Boots": "Boots",
  "Body Armours": "Body",
  "Helmets": "Helmet",
  "Shields": "Shield",
  "Amulets": "Amulet",
  "Rings": "Ring",
  "Quivers": "Quiver",
  "Belts": "Belt",
  "Jewel": "Jewel",
  "Life Flasks": "Flask",
  "Mana Flasks": "Flask",
  "Hybrid Flasks": "Flask",
  "Utility Flasks": "Flask",
  "Critical Utility Flasks": "Flask",
  "Maps": "Map",
  "Map Fragments": "Map Fragment",
  "Divination Card": "Card"
}
